[
    {
        "username": "ia_wAHZtg",
        "password": "R6adNDm3"
    },
    {
        "username": "ia_5HmNWF",
        "password": "H0Tb5dWw"
    },
    {
        "username": "ia_rNz0vN",
        "password": "CTksvsdD"
    },
    {
        "username": "ia_KeN2R9",
        "password": "dFqls0eg"
    },
    {
        "username": "ia_dtad6u",
        "password": "Dpo3MXr1"
    },
    {
        "username": "ia_bTTTwQ",
        "password": "QuyTNQFo"
    },
    {
        "username": "ia_gbNmax",
        "password": "m6kdLdHg"
    },
    {
        "username": "ia_3VEAfP",
        "password": "ujK3JDzQ"
    },
    {
        "username": "ia_vDZ7Kv",
        "password": "Ydv8DlRh"
    },
    {
        "username": "ia_UdaFtA",
        "password": "sfCRmZmg"
    },
    {
        "username": "ia_ktF9zI",
        "password": "vJXRCwfx"
    },
    {
        "username": "ia_h776aI",
        "password": "1UxdTMBy"
    },
    {
        "username": "ia_4O520f",
        "password": "pGkKxZ0E"
    },
    {
        "username": "ia_i6yIfn",
        "password": "fMnjdpwr"
    },
    {
        "username": "ia_L0e2nh",
        "password": "bqcHAHPj"
    },
    {
        "username": "ia_1ZWpHj",
        "password": "2vfUT3kt"
    },
    {
        "username": "ia_XhIYWC",
        "password": "gtMZO7CL"
    },
    {
        "username": "ia_XhX6Bb",
        "password": "6CuVkp1o"
    },
    {
        "username": "ia_VWC5t1",
        "password": "A7oNRVOF"
    },
    {
        "username": "ia_04R5gy",
        "password": "jO1KqiYA"
    },
    {
        "username": "ia_3qcEJ4",
        "password": "BheKjtmd"
    },
    {
        "username": "ia_4CCZvX",
        "password": "VFKhm0Tf"
    },
    {
        "username": "ia_DLP5Jk",
        "password": "cJGjDl1W"
    },
    {
        "username": "ia_9g1oue",
        "password": "L1g1SISX"
    },
    {
        "username": "ia_nrqXNU",
        "password": "Mlh7fOCK"
    },
    {
        "username": "ia_RDYFIO",
        "password": "ZW4zcmYc"
    },
    {
        "username": "ia_Y6V2Uz",
        "password": "ox6Pz1kV"
    },
    {
        "username": "ia_BZo4Ba",
        "password": "pIoegVIq"
    },
    {
        "username": "ia_iENM3E",
        "password": "vtqRa56d"
    },
    {
        "username": "ia_T2y21b",
        "password": "6oQ4Iyk2"
    },
    {
        "username": "ia_qHoXZf",
        "password": "YWZ31GU9"
    },
    {
        "username": "ia_aO6NYC",
        "password": "gL4EabME"
    },
    {
        "username": "ia_Jrgl4n",
        "password": "z7RrCPqW"
    },
    {
        "username": "ia_NHREQC",
        "password": "kPTxc5dm"
    },
    {
        "username": "ia_a6OFcL",
        "password": "UC0q0szg"
    },
    {
        "username": "ia_mOpIMp",
        "password": "CsJ3f5Y6"
    },
    {
        "username": "ia_uF5RKX",
        "password": "X7advzKH"
    },
    {
        "username": "ia_Znthob",
        "password": "KoPpwGjp"
    },
    {
        "username": "ia_055QIx",
        "password": "CCOnfMGM"
    },
    {
        "username": "ia_VDlntq",
        "password": "p5QoHWXe"
    },
    {
        "username": "ia_iJRxD7",
        "password": "dRrgJjHh"
    },
    {
        "username": "ia_2mY6H4",
        "password": "9jRCgOtw"
    },
    {
        "username": "ia_azUV4x",
        "password": "2WAq4dWY"
    },
    {
        "username": "ia_tTsskr",
        "password": "essGAiqV"
    },
    {
        "username": "ia_PH98SJ",
        "password": "ldEqOR5Z"
    },
    {
        "username": "ia_slZ9WU",
        "password": "w30iAdZU"
    },
    {
        "username": "ia_SJw4gh",
        "password": "L29DRTIs"
    },
    {
        "username": "ia_P31afy",
        "password": "1gdn0BBH"
    },
    {
        "username": "ia_3t3G3B",
        "password": "bdFeTMh7"
    },
    {
        "username": "ia_MbiKZ7",
        "password": "UMU3pLkh"
    },
    {
        "username": "ia_ORMFwV",
        "password": "8T0bJr5a"
    },
    {
        "username": "ia_OYI3Gp",
        "password": "5WivTx5d"
    },
    {
        "username": "ia_ul6t34",
        "password": "at63JyzQ"
    },
    {
        "username": "ia_WSicRc",
        "password": "FGzGA8cV"
    },
    {
        "username": "ia_QbXDVI",
        "password": "XRhjXRqc"
    },
    {
        "username": "ia_HqBfWe",
        "password": "2dqZFaPh"
    },
    {
        "username": "ia_tcXiPR",
        "password": "vGksV3yE"
    },
    {
        "username": "ia_h7fUpT",
        "password": "m6dzlF1C"
    },
    {
        "username": "ia_2Zsxwt",
        "password": "gtLvb5yv"
    },
    {
        "username": "ia_dZx6Vp",
        "password": "uPAuzqE7"
    },
    {
        "username": "ia_77rV3b",
        "password": "NLmzSaFL"
    },
    {
        "username": "ia_MpFJjC",
        "password": "SAHf7X03"
    },
    {
        "username": "ia_jBARUA",
        "password": "4KNsJCyY"
    },
    {
        "username": "ia_vHC9yc",
        "password": "ShvBGoFh"
    },
    {
        "username": "ia_84QHF4",
        "password": "PmFtODOE"
    },
    {
        "username": "ia_dy0Ks1",
        "password": "MTTekNEo"
    },
    {
        "username": "ia_areNeS",
        "password": "S4MgAd1P"
    },
    {
        "username": "ia_FZDD8A",
        "password": "6dTxh1FF"
    },
    {
        "username": "ia_MAUyEP",
        "password": "pL71ijEd"
    },
    {
        "username": "ia_XLzEEM",
        "password": "6LUxG4oq"
    },
    {
        "username": "ia_hPTUd2",
        "password": "di1P5umJ"
    },
    {
        "username": "ia_9J3POn",
        "password": "QuShbHnM"
    },
    {
        "username": "ia_k32jWM",
        "password": "upYSvizA"
    },
    {
        "username": "ia_RdDv5L",
        "password": "hwkHMRTX"
    },
    {
        "username": "ia_hlu9Fq",
        "password": "oOUw22kE"
    },
    {
        "username": "ia_GPyAVJ",
        "password": "UKyGToig"
    },
    {
        "username": "ia_s9gtcx",
        "password": "0hSBV6x6"
    },
    {
        "username": "ia_QT30cB",
        "password": "ETEUOZSA"
    },
    {
        "username": "ia_vnXNT5",
        "password": "Zj7mEFxB"
    },
    {
        "username": "ia_wbXzu7",
        "password": "gxeDxyOv"
    },
    {
        "username": "ia_LnBi12",
        "password": "nxLuY9yS"
    },
    {
        "username": "ia_RmySab",
        "password": "1Ga5DnGa"
    },
    {
        "username": "ia_yCTm23",
        "password": "wOUvkehs"
    },
    {
        "username": "ia_RzP8Ey",
        "password": "k4tsZlpG"
    },
    {
        "username": "ia_MZxl57",
        "password": "B5coxciK"
    },
    {
        "username": "ia_auBpdp",
        "password": "Q9sL9N87"
    },
    {
        "username": "ia_fCaMwK",
        "password": "auM3kezk"
    },
    {
        "username": "ia_AprIEv",
        "password": "7tTDrL5g"
    },
    {
        "username": "ia_uhOThy",
        "password": "V8O6vi5O"
    },
    {
        "username": "ia_JLTC7B",
        "password": "L23wTQct"
    },
    {
        "username": "ia_t9dOkI",
        "password": "tN4cdAsr"
    },
    {
        "username": "ia_dkWpYo",
        "password": "80zLRjsT"
    },
    {
        "username": "ia_Jppg1m",
        "password": "KMPrBDV7"
    },
    {
        "username": "ia_uSpUUG",
        "password": "4uv8CsaP"
    },
    {
        "username": "ia_ezpvsO",
        "password": "lk0Zfmoj"
    },
    {
        "username": "ia_fHAOBg",
        "password": "HHLOJKn3"
    },
    {
        "username": "ia_tWtu8g",
        "password": "qkBSS4gN"
    }
]